zcm/__init__.py
zcm/collapse.py
zcm/radar_bands.py
zcm/zeta_metrics.py
zcm_collapse_model-1.0.3.dist-info/METADATA
zcm_collapse_model-1.0.3.dist-info/WHEEL
zcm_collapse_model-1.0.3.dist-info/top_level.txt
zcm_collapse_model-1.0.3.dist-info/RECORD
