Metadata-Version: 2.4
Name: zcm-collapse-model
Version: 1.0.3
Summary: Math-only implementation of the Zeta Collapse Model (ZCM). System architecture and database are patent-pending and not included.
Author: Alex Veldman
License: Apache-2.0
Project-URL: Homepage, https://github.com/alexvm35/zcm-collapse-model
Project-URL: Source, https://github.com/alexvm35/zcm-collapse-model
Project-URL: Issue Tracker, https://github.com/alexvm35/zcm-collapse-model/issues
Keywords: zeta,zeta-function,collapse-model,deterministic,entropy-reduction,harmonic-analysis,signal-processing,math-library,python-library
Classifier: Programming Language :: Python :: 3
Classifier: Programming Language :: Python :: 3 :: Only
Classifier: License :: OSI Approved :: Apache Software License
Classifier: Intended Audience :: Science/Research
Classifier: Topic :: Scientific/Engineering :: Mathematics
Requires-Python: >=3.9
